MANIFEST.in
README.txt
setup.cfg
setup.py
asv_seo/__init__.py
asv_seo/admin.py
asv_seo/cache.py
asv_seo/models.py
asv_seo/urls.py
asv_seo/utils.py
asv_seo/views.py
asv_seo.egg-info/PKG-INFO
asv_seo.egg-info/SOURCES.txt
asv_seo.egg-info/dependency_links.txt
asv_seo.egg-info/not-zip-safe
asv_seo.egg-info/requires.txt
asv_seo.egg-info/top_level.txt
asv_seo/migrations/0001_initial.py
asv_seo/migrations/0002_auto__add_field_analperm_site__add_field_analperm_de__add_field_analpe.py
asv_seo/migrations/0003_auto__add_field_webcounter_site__del_field_analperm_site.py
asv_seo/migrations/0004_auto__add_robotstxt.py
asv_seo/migrations/0005_auto__del_field_robotstxt_name.py
asv_seo/migrations/__init__.py
asv_seo/templates/asv_seo/ic_seo_headers.html
asv_seo/templates/asv_seo/ic_web_counters.html
asv_seo/templatetags/__init__.py
asv_seo/templatetags/asv_seo_tags.py