Metadata-Version: 1.0
Name: asv-seo
Version: dev-20120329-04
Summary: This module contains some batteries for Django:
